LICENSE
README.rst
pyNNST.py
setup.py
pyNNST.egg-info/PKG-INFO
pyNNST.egg-info/SOURCES.txt
pyNNST.egg-info/dependency_links.txt
pyNNST.egg-info/requires.txt
pyNNST.egg-info/top_level.txt