Metadata-Version: 2.4
Name: pyNNST
Version: 0.2
Summary: Definition of non-stationary index for time-series
Home-page: https://github.com/LolloCappo/pyNNST
Author: Lorenzo Capponi
Author-email: lorenzocapponi@outlook.it
License-File: LICENSE
Requires-Dist: numpy
Dynamic: author
Dynamic: author-email
Dynamic: description
Dynamic: home-page
Dynamic: license-file
Dynamic: requires-dist
Dynamic: summary
